CHANGELOG.md
LICENSE
MANIFEST.in
README.md
setup.cfg
setup.py
django_templatestore.egg-info/PKG-INFO
django_templatestore.egg-info/SOURCES.txt
django_templatestore.egg-info/dependency_links.txt
django_templatestore.egg-info/top_level.txt
example/__init__.py
example/asgi.py
example/settings.py
example/urls.py
example/wsgi.py
templatestore/__init__.py
templatestore/app_settings.py
templatestore/apps.py
templatestore/models.py
templatestore/tests.py
templatestore/urls.py
templatestore/views.py
templatestore/frontend/dist/te-bundle.js
templatestore/migrations/0001_initial.py
templatestore/migrations/__init__.py
templatestore/templates/index.html